{
    "kind": "youtube#searchListResponse",
    "etag": "ESbD9CDAv1FWY0FRW-pqHlW1JP4",
    "nextPageToken": "CDIQAA",
    "regionCode": "IN",
    "pageInfo": {
      "totalResults": 1000000,
      "resultsPerPage": 50
    },
    "items": [
      {
        "kind": "youtube#searchResult",
        "etag": "AH5Z5pBmA1BZ_TCzeYruKVRmXXc",
        "id": {
          "kind": "youtube#video",
          "videoId": "AiCI-DQ11bw"
        },
        "snippet": {
          "publishedAt": "2025-03-26T10:11:29Z",
          "channelId": "UCZy7vibLOxrNyngoHJByZfw",
          "title": "Diamond Gameplay 🫡 | Valorant Gaming LALA | New Game Later",
          "description": "My Official Clothing Brand - https://altf4.in/ ▻ ROG World's Most Premium Gaming Laptop Brand, To know More ...",
          "thumbnails": {
            "default": {
              "url": "https://i.ytimg.com/vi/AiCI-DQ11bw/default_live.jpg",
              "width": 120,
              "height": 90
            },
            "medium": {
              "url": "https://i.ytimg.com/vi/AiCI-DQ11bw/mqdefault_live.jpg",
              "width": 320,
              "height": 180
            },
            "high": {
              "url": "https://i.ytimg.com/vi/AiCI-DQ11bw/hqdefault_live.jpg",
              "width": 480,
              "height": 360
            }
          },
          "channelTitle": "Harsh Khelraay",
          "liveBroadcastContent": "live",
          "publishTime": "2025-03-26T10:11:29Z"
        }
      },
      {
        "kind": "youtube#searchResult",
        "etag": "4uOyFkrEthaX-42SzwaN5BmwSHo",
        "id": {
          "kind": "youtube#video",
          "videoId": "eixaFYJULg4"
        },
        "snippet": {
          "publishedAt": "2025-03-14T21:24:17Z",
          "channelId": "UCNFT_eq_QCApMEwCACHto9Q",
          "title": "Gaming at 3am 💀",
          "description": "",
          "thumbnails": {
            "default": {
              "url": "https://i.ytimg.com/vi/eixaFYJULg4/default.jpg",
              "width": 120,
              "height": 90
            },
            "medium": {
              "url": "https://i.ytimg.com/vi/eixaFYJULg4/mqdefault.jpg",
              "width": 320,
              "height": 180
            },
            "high": {
              "url": "https://i.ytimg.com/vi/eixaFYJULg4/hqdefault.jpg",
              "width": 480,
              "height": 360
            }
          },
          "channelTitle": "Speed McQueen ",
          "liveBroadcastContent": "none",
          "publishTime": "2025-03-14T21:24:17Z"
        }
      },
      {
        "kind": "youtube#searchResult",
        "etag": "_PpnXLoHXC7NYAhbnIDzdPrI-9I",
        "id": {
          "kind": "youtube#video",
          "videoId": "cNlBAvSwj1M"
        },
        "snippet": {
          "publishedAt": "2025-03-26T08:20:06Z",
          "channelId": "UCxMjcJPl9SRTGb7ufFMiLCg",
          "title": "Lets Master 120 FPS | Anony Gaming is Live",
          "description": "Join this channel to get access to perks: https://www.youtube.com/channel/UCxMjcJPl9SRTGb7ufFMiLCg/join handcam Video ...",
          "thumbnails": {
            "default": {
              "url": "https://i.ytimg.com/vi/cNlBAvSwj1M/default_live.jpg",
              "width": 120,
              "height": 90
            },
            "medium": {
              "url": "https://i.ytimg.com/vi/cNlBAvSwj1M/mqdefault_live.jpg",
              "width": 320,
              "height": 180
            },
            "high": {
              "url": "https://i.ytimg.com/vi/cNlBAvSwj1M/hqdefault_live.jpg",
              "width": 480,
              "height": 360
            }
          },
          "channelTitle": "Anony Gaming",
          "liveBroadcastContent": "live",
          "publishTime": "2025-03-26T08:20:06Z"
        }
      },
      {
        "kind": "youtube#searchResult",
        "etag": "Tn6RZq3w91c8MF3-a4WAwsIUWwM",
        "id": {
          "kind": "youtube#video",
          "videoId": "z4xAwyOYIdM"
        },
        "snippet": {
          "publishedAt": "2024-08-30T02:26:34Z",
          "channelId": "UCHRgGoDEDXppl8j0BvhFuGg",
          "title": "Karma ☠️😈 #shorts #scary #granny #ytshorts #nostalgia",
          "description": "",
          "thumbnails": {
            "default": {
              "url": "https://i.ytimg.com/vi/z4xAwyOYIdM/default.jpg",
              "width": 120,
              "height": 90
            },
            "medium": {
              "url": "https://i.ytimg.com/vi/z4xAwyOYIdM/mqdefault.jpg",
              "width": 320,
              "height": 180
            },
            "high": {
              "url": "https://i.ytimg.com/vi/z4xAwyOYIdM/hqdefault.jpg",
              "width": 480,
              "height": 360
            }
          },
          "channelTitle": "Rohit Gaming",
          "liveBroadcastContent": "none",
          "publishTime": "2024-08-30T02:26:34Z"
        }
      },
      {
        "kind": "youtube#searchResult",
        "etag": "Of849RvLx9fsg3nrsf_0TrcvOoE",
        "id": {
          "kind": "youtube#video",
          "videoId": "m9g7WoQytjI"
        },
        "snippet": {
          "publishedAt": "2024-12-29T12:31:16Z",
          "channelId": "UCe4bubvNWxeD_Tjj6PpVBDA",
          "title": "💀Longest Sniper Shot #bgmi #gaming",
          "description": "Longest Sniper Shot #bgmi #gaming.",
          "thumbnails": {
            "default": {
              "url": "https://i.ytimg.com/vi/m9g7WoQytjI/default.jpg",
              "width": 120,
              "height": 90
            },
            "medium": {
              "url": "https://i.ytimg.com/vi/m9g7WoQytjI/mqdefault.jpg",
              "width": 320,
              "height": 180
            },
            "high": {
              "url": "https://i.ytimg.com/vi/m9g7WoQytjI/hqdefault.jpg",
              "width": 480,
              "height": 360
            }
          },
          "channelTitle": "THE LEGIT GAMING",
          "liveBroadcastContent": "none",
          "publishTime": "2024-12-29T12:31:16Z"
        }
      },
      {
        "kind": "youtube#searchResult",
        "etag": "xJEY7xcZDO0C8J6B2SSO6nd1stU",
        "id": {
          "kind": "youtube#video",
          "videoId": "FJG7aL7GA0U"
        },
        "snippet": {
          "publishedAt": "2024-06-23T10:01:01Z",
          "channelId": "UCyY4krBsUGzoj1Cjyj4nZqQ",
          "title": "Shopping Mall Me Jakar Game Khela 🙄😂😁#viral #funny #shorts",
          "description": "",
          "thumbnails": {
            "default": {
              "url": "https://i.ytimg.com/vi/FJG7aL7GA0U/default.jpg",
              "width": 120,
              "height": 90
            },
            "medium": {
              "url": "https://i.ytimg.com/vi/FJG7aL7GA0U/mqdefault.jpg",
              "width": 320,
              "height": 180
            },
            "high": {
              "url": "https://i.ytimg.com/vi/FJG7aL7GA0U/hqdefault.jpg",
              "width": 480,
              "height": 360
            }
          },
          "channelTitle": "Apu Alone",
          "liveBroadcastContent": "none",
          "publishTime": "2024-06-23T10:01:01Z"
        }
      },
      {
        "kind": "youtube#searchResult",
        "etag": "A9Vx_aerIFDuEoHXSPJeaztvlRU",
        "id": {
          "kind": "youtube#video",
          "videoId": "6KGQTbYkVq4"
        },
        "snippet": {
          "publishedAt": "2025-01-24T14:00:05Z",
          "channelId": "UCJJiCsW19n6fdoxcUMvcitQ",
          "title": "Pov : you brought  your IPod to Squid Games #funny #roblox #squidgame #animation",
          "description": "",
          "thumbnails": {
            "default": {
              "url": "https://i.ytimg.com/vi/6KGQTbYkVq4/default.jpg",
              "width": 120,
              "height": 90
            },
            "medium": {
              "url": "https://i.ytimg.com/vi/6KGQTbYkVq4/mqdefault.jpg",
              "width": 320,
              "height": 180
            },
            "high": {
              "url": "https://i.ytimg.com/vi/6KGQTbYkVq4/hqdefault.jpg",
              "width": 480,
              "height": 360
            }
          },
          "channelTitle": "Draw For Fun",
          "liveBroadcastContent": "none",
          "publishTime": "2025-01-24T14:00:05Z"
        }
      },
      {
        "kind": "youtube#searchResult",
        "etag": "WhqPs0mPDSxYxzXYdwCV0r-6GQU",
        "id": {
          "kind": "youtube#video",
          "videoId": "Cj-YHr6nUTs"
        },
        "snippet": {
          "publishedAt": "2025-03-26T06:40:51Z",
          "channelId": "UCzlb7-RxHTU8WriwZUE2qWw",
          "title": "STAR&#39;O KE STARS 🌟  GRP-D 🔥🚀 FT- NG, CFF, TE, VE, DC, PP, FOZYAJAY 🥵 #nonstopgaming -free fire live",
          "description": "1 vs 5 TESTING YOUTUBERS FROM INDIA , VIETNAM , BD ? #nonstopgaming -free fire live STAR'O KE STARS ...",
          "thumbnails": {
            "default": {
              "url": "https://i.ytimg.com/vi/Cj-YHr6nUTs/default_live.jpg",
              "width": 120,
              "height": 90
            },
            "medium": {
              "url": "https://i.ytimg.com/vi/Cj-YHr6nUTs/mqdefault_live.jpg",
              "width": 320,
              "height": 180
            },
            "high": {
              "url": "https://i.ytimg.com/vi/Cj-YHr6nUTs/hqdefault_live.jpg",
              "width": 480,
              "height": 360
            }
          },
          "channelTitle": "Nonstop Gaming",
          "liveBroadcastContent": "live",
          "publishTime": "2025-03-26T06:40:51Z"
        }
      },
      {
        "kind": "youtube#searchResult",
        "etag": "tFCVRliHVJGLyHnpTNNvleyB8t4",
        "id": {
          "kind": "youtube#video",
          "videoId": "gNWy2nrNUbU"
        },
        "snippet": {
          "publishedAt": "2025-02-14T13:00:58Z",
          "channelId": "UCtxbV-l2t708Y4tkGSn2IZg",
          "title": "Weirdest AFK Easter Eggs in Gaming 🙃",
          "description": "Watch me LIVE at https://www.twitch.tv/bundun Follow me on Twitter at https://twitter.com/BundunLive Business Email: ...",
          "thumbnails": {
            "default": {
              "url": "https://i.ytimg.com/vi/gNWy2nrNUbU/default.jpg",
              "width": 120,
              "height": 90
            },
            "medium": {
              "url": "https://i.ytimg.com/vi/gNWy2nrNUbU/mqdefault.jpg",
              "width": 320,
              "height": 180
            },
            "high": {
              "url": "https://i.ytimg.com/vi/gNWy2nrNUbU/hqdefault.jpg",
              "width": 480,
              "height": 360
            }
          },
          "channelTitle": "Bundun",
          "liveBroadcastContent": "none",
          "publishTime": "2025-02-14T13:00:58Z"
        }
      },
      {
        "kind": "youtube#searchResult",
        "etag": "3JkiVrE9RM0MOeIZ5AfD56paVpM",
        "id": {
          "kind": "youtube#video",
          "videoId": "HIgqWSJwfmY"
        },
        "snippet": {
          "publishedAt": "2024-09-20T03:00:15Z",
          "channelId": "UCRC7VhUZvbZ0ftr-AWUBFKA",
          "title": "Kamla vs tillu reporter 😂 || kamla Indian horror game #shorts",
          "description": "Kamla tillu reporter and interview || kamla Indian horror game #shorts Kamla Kamla horror game Kamla game Horror games ...",
          "thumbnails": {
            "default": {
              "url": "https://i.ytimg.com/vi/HIgqWSJwfmY/default.jpg",
              "width": 120,
              "height": 90
            },
            "medium": {
              "url": "https://i.ytimg.com/vi/HIgqWSJwfmY/mqdefault.jpg",
              "width": 320,
              "height": 180
            },
            "high": {
              "url": "https://i.ytimg.com/vi/HIgqWSJwfmY/hqdefault.jpg",
              "width": 480,
              "height": 360
            }
          },
          "channelTitle": "EMULATION GAMER",
          "liveBroadcastContent": "none",
          "publishTime": "2024-09-20T03:00:15Z"
        }
      },
      {
        "kind": "youtube#searchResult",
        "etag": "6ASWX1InZWAo7U_zlBIF9DeL6Bg",
        "id": {
          "kind": "youtube#video",
          "videoId": "s7s4JBh6ZF8"
        },
        "snippet": {
          "publishedAt": "2025-01-01T13:47:26Z",
          "channelId": "UCUnmH8N8k4E7y3dKfCzDKKg",
          "title": "POV: You fell into Squid Game... #Netflixpartner",
          "description": "Click the links below for more behind the scenes and exclusive content! Tiktok: https://www.tiktok.com/@brandonb ...",
          "thumbnails": {
            "default": {
              "url": "https://i.ytimg.com/vi/s7s4JBh6ZF8/default.jpg",
              "width": 120,
              "height": 90
            },
            "medium": {
              "url": "https://i.ytimg.com/vi/s7s4JBh6ZF8/mqdefault.jpg",
              "width": 320,
              "height": 180
            },
            "high": {
              "url": "https://i.ytimg.com/vi/s7s4JBh6ZF8/hqdefault.jpg",
              "width": 480,
              "height": 360
            }
          },
          "channelTitle": "Brandon B",
          "liveBroadcastContent": "none",
          "publishTime": "2025-01-01T13:47:26Z"
        }
      },
      {
        "kind": "youtube#searchResult",
        "etag": "UXhM_2Rtz4mjlLmo7voEHQGBCLA",
        "id": {
          "kind": "youtube#video",
          "videoId": "AvcdY_tuBeU"
        },
        "snippet": {
          "publishedAt": "2024-12-01T13:16:21Z",
          "channelId": "UC77Fy5PwlSnon_NNoCYSQEg",
          "title": "Minecraft Squid Games 3 💀",
          "description": "",
          "thumbnails": {
            "default": {
              "url": "https://i.ytimg.com/vi/AvcdY_tuBeU/default.jpg",
              "width": 120,
              "height": 90
            },
            "medium": {
              "url": "https://i.ytimg.com/vi/AvcdY_tuBeU/mqdefault.jpg",
              "width": 320,
              "height": 180
            },
            "high": {
              "url": "https://i.ytimg.com/vi/AvcdY_tuBeU/hqdefault.jpg",
              "width": 480,
              "height": 360
            }
          },
          "channelTitle": "HamoodeG",
          "liveBroadcastContent": "none",
          "publishTime": "2024-12-01T13:16:21Z"
        }
      },
      {
        "kind": "youtube#searchResult",
        "etag": "34yI3__coLaJ_qUcIuQtzUFTCfc",
        "id": {
          "kind": "youtube#video",
          "videoId": "fOhvuzDBrJ8"
        },
        "snippet": {
          "publishedAt": "2025-01-04T15:25:00Z",
          "channelId": "UCpQuf-xha2xRmLdTEVPQCOw",
          "title": "Minecraft 💀 #minecraft #fyp #viral #shorts",
          "description": "Minecraft #minecraft #fyp #viral #shorts #minecraft #madapgaming https://discord.gg/8FwzsaP3vr Join the discord Music ...",
          "thumbnails": {
            "default": {
              "url": "https://i.ytimg.com/vi/fOhvuzDBrJ8/default.jpg",
              "width": 120,
              "height": 90
            },
            "medium": {
              "url": "https://i.ytimg.com/vi/fOhvuzDBrJ8/mqdefault.jpg",
              "width": 320,
              "height": 180
            },
            "high": {
              "url": "https://i.ytimg.com/vi/fOhvuzDBrJ8/hqdefault.jpg",
              "width": 480,
              "height": 360
            }
          },
          "channelTitle": "Mayank gaming ",
          "liveBroadcastContent": "none",
          "publishTime": "2025-01-04T15:25:00Z"
        }
      },
      {
        "kind": "youtube#searchResult",
        "etag": "AclqfezWO6QO7asSTgS7MCrnymo",
        "id": {
          "kind": "youtube#video",
          "videoId": "M7KpogdgoAM"
        },
        "snippet": {
          "publishedAt": "2025-03-01T09:00:22Z",
          "channelId": "UCrddA2HWyVhVmU3X63oJMgg",
          "title": "Age of Apes ads review new level: Ape Uprising Begins #gaming #games #funny",
          "description": "",
          "thumbnails": {
            "default": {
              "url": "https://i.ytimg.com/vi/M7KpogdgoAM/default.jpg",
              "width": 120,
              "height": 90
            },
            "medium": {
              "url": "https://i.ytimg.com/vi/M7KpogdgoAM/mqdefault.jpg",
              "width": 320,
              "height": 180
            },
            "high": {
              "url": "https://i.ytimg.com/vi/M7KpogdgoAM/hqdefault.jpg",
              "width": 480,
              "height": 360
            }
          },
          "channelTitle": "AOA Review",
          "liveBroadcastContent": "none",
          "publishTime": "2025-03-01T09:00:22Z"
        }
      },
      {
        "kind": "youtube#searchResult",
        "etag": "O3-fCbN1EkFAx1QbYwGT62O1r98",
        "id": {
          "kind": "youtube#video",
          "videoId": "hZWNRBEdVpQ"
        },
        "snippet": {
          "publishedAt": "2024-09-26T15:00:47Z",
          "channelId": "UCuwJoiGWRxPYStBp0l0WuZw",
          "title": "Gaming As A Kid VS Now #Shorts",
          "description": "Gaming As A Kid VS Now #Shorts.",
          "thumbnails": {
            "default": {
              "url": "https://i.ytimg.com/vi/hZWNRBEdVpQ/default.jpg",
              "width": 120,
              "height": 90
            },
            "medium": {
              "url": "https://i.ytimg.com/vi/hZWNRBEdVpQ/mqdefault.jpg",
              "width": 320,
              "height": 180
            },
            "high": {
              "url": "https://i.ytimg.com/vi/hZWNRBEdVpQ/hqdefault.jpg",
              "width": 480,
              "height": 360
            }
          },
          "channelTitle": "Luke Davidson",
          "liveBroadcastContent": "none",
          "publishTime": "2024-09-26T15:00:47Z"
        }
      },
      {
        "kind": "youtube#searchResult",
        "etag": "RkKS8vAdJ-VEVv2VeQFUJrKVaKo",
        "id": {
          "kind": "youtube#video",
          "videoId": "QF3sZ8sR4jc"
        },
        "snippet": {
          "publishedAt": "2024-08-23T05:35:12Z",
          "channelId": "UCv114ShUgWNYqk2G-13Y3Mg",
          "title": "Indian bike 3d game 😄 new Thar and Porsche all Lamborghini and bike ZX10r the KTM and R15",
          "description": "",
          "thumbnails": {
            "default": {
              "url": "https://i.ytimg.com/vi/QF3sZ8sR4jc/default.jpg",
              "width": 120,
              "height": 90
            },
            "medium": {
              "url": "https://i.ytimg.com/vi/QF3sZ8sR4jc/mqdefault.jpg",
              "width": 320,
              "height": 180
            },
            "high": {
              "url": "https://i.ytimg.com/vi/QF3sZ8sR4jc/hqdefault.jpg",
              "width": 480,
              "height": 360
            }
          },
          "channelTitle": "AK GAMRZ",
          "liveBroadcastContent": "none",
          "publishTime": "2024-08-23T05:35:12Z"
        }
      },
      {
        "kind": "youtube#searchResult",
        "etag": "Bp8aiQ4vzPjUm9Hu6nJPA6MpFyI",
        "id": {
          "kind": "youtube#video",
          "videoId": "uw0IgZoR940"
        },
        "snippet": {
          "publishedAt": "2023-10-13T09:00:35Z",
          "channelId": "UCMrvxKTx9hLhZcOvJkYOnAw",
          "title": "Tonde Gamer Vs As Gaming 😂Collection Versus #shorts #freefire",
          "description": "Tonde Gamer Vs As Gaming Collection Versus #shorts #freefire GAME NAME - Garena Free Fire Garena freefire Live ...",
          "thumbnails": {
            "default": {
              "url": "https://i.ytimg.com/vi/uw0IgZoR940/default.jpg",
              "width": 120,
              "height": 90
            },
            "medium": {
              "url": "https://i.ytimg.com/vi/uw0IgZoR940/mqdefault.jpg",
              "width": 320,
              "height": 180
            },
            "high": {
              "url": "https://i.ytimg.com/vi/uw0IgZoR940/hqdefault.jpg",
              "width": 480,
              "height": 360
            }
          },
          "channelTitle": "AS Gaming",
          "liveBroadcastContent": "none",
          "publishTime": "2023-10-13T09:00:35Z"
        }
      },
      {
        "kind": "youtube#searchResult",
        "etag": "WhlUr50b_Hp55bUGciREIYQsuiY",
        "id": {
          "kind": "youtube#video",
          "videoId": "IpkThzFR06U"
        },
        "snippet": {
          "publishedAt": "2024-01-17T16:11:39Z",
          "channelId": "UCBGbTTcgn8AVEsEWdT3tI3Q",
          "title": "1% CHANCE OF THIS HAPPENING AND IT HAPPENS... #buckshotroulette #igp #gaming",
          "description": "FULL VIDEO: https://youtu.be/ilzh9Kkkpw0 Play Buckshot Roulette: https://mikeklubnika.itch.io/buckshot-roulette Previous ...",
          "thumbnails": {
            "default": {
              "url": "https://i.ytimg.com/vi/IpkThzFR06U/default.jpg",
              "width": 120,
              "height": 90
            },
            "medium": {
              "url": "https://i.ytimg.com/vi/IpkThzFR06U/mqdefault.jpg",
              "width": 320,
              "height": 180
            },
            "high": {
              "url": "https://i.ytimg.com/vi/IpkThzFR06U/hqdefault.jpg",
              "width": 480,
              "height": 360
            }
          },
          "channelTitle": "IGP",
          "liveBroadcastContent": "none",
          "publishTime": "2024-01-17T16:11:39Z"
        }
      },
      {
        "kind": "youtube#searchResult",
        "etag": "u97CFOD3S_3RehHET9yL5fYDy1E",
        "id": {
          "kind": "youtube#video",
          "videoId": "MxSog0rv5Lg"
        },
        "snippet": {
          "publishedAt": "2024-10-28T13:00:23Z",
          "channelId": "UC6QZ_ss3i_8qLV_RczPZBkw",
          "title": "The Game of Life🎮",
          "description": "Welcome to the energetic and funny ISSEI Channel!! Please subscribe if you like this videos, and hit the Like button and Share!",
          "thumbnails": {
            "default": {
              "url": "https://i.ytimg.com/vi/MxSog0rv5Lg/default.jpg",
              "width": 120,
              "height": 90
            },
            "medium": {
              "url": "https://i.ytimg.com/vi/MxSog0rv5Lg/mqdefault.jpg",
              "width": 320,
              "height": 180
            },
            "high": {
              "url": "https://i.ytimg.com/vi/MxSog0rv5Lg/hqdefault.jpg",
              "width": 480,
              "height": 360
            }
          },
          "channelTitle": "ISSEI / いっせい",
          "liveBroadcastContent": "none",
          "publishTime": "2024-10-28T13:00:23Z"
        }
      },
      {
        "kind": "youtube#searchResult",
        "etag": "TB-gsJfKf_vqQZZoW3zuaV2JOb0",
        "id": {
          "kind": "youtube#video",
          "videoId": "-4tesAWfZVk"
        },
        "snippet": {
          "publishedAt": "2024-08-18T11:00:00Z",
          "channelId": "UCrddA2HWyVhVmU3X63oJMgg",
          "title": "Age of Apes ads review new level: Worms invade the body #games #gaming #gameape",
          "description": "",
          "thumbnails": {
            "default": {
              "url": "https://i.ytimg.com/vi/-4tesAWfZVk/default.jpg",
              "width": 120,
              "height": 90
            },
            "medium": {
              "url": "https://i.ytimg.com/vi/-4tesAWfZVk/mqdefault.jpg",
              "width": 320,
              "height": 180
            },
            "high": {
              "url": "https://i.ytimg.com/vi/-4tesAWfZVk/hqdefault.jpg",
              "width": 480,
              "height": 360
            }
          },
          "channelTitle": "AOA Review",
          "liveBroadcastContent": "none",
          "publishTime": "2024-08-18T11:00:00Z"
        }
      },
      {
        "kind": "youtube#searchResult",
        "etag": "oPVuqZtBNfEyWrVNPXDIQRTyr_s",
        "id": {
          "kind": "youtube#video",
          "videoId": "fGVZQ5cSfyI"
        },
        "snippet": {
          "publishedAt": "2024-06-07T16:40:26Z",
          "channelId": "UC0oI44ZUVCqq4meNOOaKPTQ",
          "title": "Every gamer needs one",
          "description": "If you're a gamer we all want one of these! #gamers #gaming #ps5 #xbox #pcgaming.",
          "thumbnails": {
            "default": {
              "url": "https://i.ytimg.com/vi/fGVZQ5cSfyI/default.jpg",
              "width": 120,
              "height": 90
            },
            "medium": {
              "url": "https://i.ytimg.com/vi/fGVZQ5cSfyI/mqdefault.jpg",
              "width": 320,
              "height": 180
            },
            "high": {
              "url": "https://i.ytimg.com/vi/fGVZQ5cSfyI/hqdefault.jpg",
              "width": 480,
              "height": 360
            }
          },
          "channelTitle": "SpawnPoiint",
          "liveBroadcastContent": "none",
          "publishTime": "2024-06-07T16:40:26Z"
        }
      },
      {
        "kind": "youtube#searchResult",
        "etag": "RcXtMX5Q0Zxx5Jnwq8eIH12Rbtc",
        "id": {
          "kind": "youtube#video",
          "videoId": "2-67twDuY-Q"
        },
        "snippet": {
          "publishedAt": "2023-12-02T11:27:43Z",
          "channelId": "UCsIiIEGRoBILi8LSkWNPqXA",
          "title": "Gaming now vs Then. #shorts #gaming #viral #funny",
          "description": "Gaming now vs Then. #shorts #gaming #viral #funny.",
          "thumbnails": {
            "default": {
              "url": "https://i.ytimg.com/vi/2-67twDuY-Q/default.jpg",
              "width": 120,
              "height": 90
            },
            "medium": {
              "url": "https://i.ytimg.com/vi/2-67twDuY-Q/mqdefault.jpg",
              "width": 320,
              "height": 180
            },
            "high": {
              "url": "https://i.ytimg.com/vi/2-67twDuY-Q/hqdefault.jpg",
              "width": 480,
              "height": 360
            }
          },
          "channelTitle": "Danucd",
          "liveBroadcastContent": "none",
          "publishTime": "2023-12-02T11:27:43Z"
        }
      },
      {
        "kind": "youtube#searchResult",
        "etag": "jbKBj-2D0soYT5-US5hoKB0M2I8",
        "id": {
          "kind": "youtube#video",
          "videoId": "rzTPRZ5zWxU"
        },
        "snippet": {
          "publishedAt": "2025-02-19T20:50:00Z",
          "channelId": "UCOduZSxYlUt-rOVSt49dKfQ",
          "title": "Chance of survival with different vehicles #beamng #beamngdrive #game #gaming #car #cars",
          "description": "",
          "thumbnails": {
            "default": {
              "url": "https://i.ytimg.com/vi/rzTPRZ5zWxU/default.jpg",
              "width": 120,
              "height": 90
            },
            "medium": {
              "url": "https://i.ytimg.com/vi/rzTPRZ5zWxU/mqdefault.jpg",
              "width": 320,
              "height": 180
            },
            "high": {
              "url": "https://i.ytimg.com/vi/rzTPRZ5zWxU/hqdefault.jpg",
              "width": 480,
              "height": 360
            }
          },
          "channelTitle": "CrashWizards",
          "liveBroadcastContent": "none",
          "publishTime": "2025-02-19T20:50:00Z"
        }
      },
      {
        "kind": "youtube#searchResult",
        "etag": "fVTBY--sbS3kNYpxfXkewytnZ54",
        "id": {
          "kind": "youtube#video",
          "videoId": "IWk0t1KrW9I"
        },
        "snippet": {
          "publishedAt": "2025-02-05T11:29:28Z",
          "channelId": "UCe4bubvNWxeD_Tjj6PpVBDA",
          "title": "💀Best Sniper Shot Ever #bgmi #pubgmobile #gaming",
          "description": "Best Sniper Shot Ever #bgmi #pubgmobile #gaming.",
          "thumbnails": {
            "default": {
              "url": "https://i.ytimg.com/vi/IWk0t1KrW9I/default.jpg",
              "width": 120,
              "height": 90
            },
            "medium": {
              "url": "https://i.ytimg.com/vi/IWk0t1KrW9I/mqdefault.jpg",
              "width": 320,
              "height": 180
            },
            "high": {
              "url": "https://i.ytimg.com/vi/IWk0t1KrW9I/hqdefault.jpg",
              "width": 480,
              "height": 360
            }
          },
          "channelTitle": "THE LEGIT GAMING",
          "liveBroadcastContent": "none",
          "publishTime": "2025-02-05T11:29:28Z"
        }
      },
      {
        "kind": "youtube#searchResult",
        "etag": "7eAjcs8TUN32Ehcd8UnB_-gGji8",
        "id": {
          "kind": "youtube#video",
          "videoId": "SeYgoLpzFlM"
        },
        "snippet": {
          "publishedAt": "2025-01-16T03:18:46Z",
          "channelId": "UCSnyFNVsXYlBLv7J75yr32Q",
          "title": "Squid game🔥😂 crazy  |  pink soldiers Funny ✅🤣 moments   #funny #pinksoldiers squidgame2|",
          "description": "Disclaimer: I do not own the copyrights of this video The Copyrights belong to the respective owners ✓ #game ...",
          "thumbnails": {
            "default": {
              "url": "https://i.ytimg.com/vi/SeYgoLpzFlM/default.jpg",
              "width": 120,
              "height": 90
            },
            "medium": {
              "url": "https://i.ytimg.com/vi/SeYgoLpzFlM/mqdefault.jpg",
              "width": 320,
              "height": 180
            },
            "high": {
              "url": "https://i.ytimg.com/vi/SeYgoLpzFlM/hqdefault.jpg",
              "width": 480,
              "height": 360
            }
          },
          "channelTitle": "One Man's Choice",
          "liveBroadcastContent": "none",
          "publishTime": "2025-01-16T03:18:46Z"
        }
      },
      {
        "kind": "youtube#searchResult",
        "etag": "tj8qUHiTbYODcp7RhKa3fA-kKtg",
        "id": {
          "kind": "youtube#video",
          "videoId": "RvNj83x14Nc"
        },
        "snippet": {
          "publishedAt": "2025-03-13T08:04:16Z",
          "channelId": "UCWKagn7v9totM0BX57-d4cQ",
          "title": "kamla game new graphics😱|kamla Horror game new update|kamla mobile graphics test|#kamla",
          "description": "kamla game new graphics  |kamla Horror game new update|kamla mobile graphics test|#kamla welcome Back Gaming ka nya ...",
          "thumbnails": {
            "default": {
              "url": "https://i.ytimg.com/vi/RvNj83x14Nc/default.jpg",
              "width": 120,
              "height": 90
            },
            "medium": {
              "url": "https://i.ytimg.com/vi/RvNj83x14Nc/mqdefault.jpg",
              "width": 320,
              "height": 180
            },
            "high": {
              "url": "https://i.ytimg.com/vi/RvNj83x14Nc/hqdefault.jpg",
              "width": 480,
              "height": 360
            }
          },
          "channelTitle": "Welcome Back Gaming",
          "liveBroadcastContent": "none",
          "publishTime": "2025-03-13T08:04:16Z"
        }
      },
      {
        "kind": "youtube#searchResult",
        "etag": "PopyCv3vYtH95KHiaF4eJvUvPhA",
        "id": {
          "kind": "youtube#video",
          "videoId": "mltkqprOI88"
        },
        "snippet": {
          "publishedAt": "2024-05-17T01:30:19Z",
          "channelId": "UClCe18fwE4Gtr7vgqka1Zlg",
          "title": "Finally! END OF KAMLA | INDIAN HORROR GAME | Part 2 #gamingengineer",
          "description": "Ending Scene Of Kamla Horror Game/ Indian Horror Game Game By: @madmantragames #liveengineer #gameplay ...",
          "thumbnails": {
            "default": {
              "url": "https://i.ytimg.com/vi/mltkqprOI88/default.jpg",
              "width": 120,
              "height": 90
            },
            "medium": {
              "url": "https://i.ytimg.com/vi/mltkqprOI88/mqdefault.jpg",
              "width": 320,
              "height": 180
            },
            "high": {
              "url": "https://i.ytimg.com/vi/mltkqprOI88/hqdefault.jpg",
              "width": 480,
              "height": 360
            }
          },
          "channelTitle": "Live Engineer",
          "liveBroadcastContent": "none",
          "publishTime": "2024-05-17T01:30:19Z"
        }
      },
      {
        "kind": "youtube#searchResult",
        "etag": "ktjG6Bv8BWgpi-H-Wlw4p1mDZec",
        "id": {
          "kind": "youtube#video",
          "videoId": "5cw7LZk1Lu0"
        },
        "snippet": {
          "publishedAt": "2025-02-18T21:56:20Z",
          "channelId": "UCB_CCSAGP_YCuR36_w2bG1w",
          "title": "Horror games today vs. back then",
          "description": "shorts Why do the pixelated graphics make the game more scary? lol Join my discord server: https://discord.gg/nYAdBdtsCh ...",
          "thumbnails": {
            "default": {
              "url": "https://i.ytimg.com/vi/5cw7LZk1Lu0/default.jpg",
              "width": 120,
              "height": 90
            },
            "medium": {
              "url": "https://i.ytimg.com/vi/5cw7LZk1Lu0/mqdefault.jpg",
              "width": 320,
              "height": 180
            },
            "high": {
              "url": "https://i.ytimg.com/vi/5cw7LZk1Lu0/hqdefault.jpg",
              "width": 480,
              "height": 360
            }
          },
          "channelTitle": "Greg Renko",
          "liveBroadcastContent": "none",
          "publishTime": "2025-02-18T21:56:20Z"
        }
      },
      {
        "kind": "youtube#searchResult",
        "etag": "msG1D67G7vIffiYpsOdvHiiGfrg",
        "id": {
          "kind": "youtube#video",
          "videoId": "dRZ1m1LnGXg"
        },
        "snippet": {
          "publishedAt": "2024-04-24T12:40:17Z",
          "channelId": "UCvrH4p4804i119JtUjtNpZQ",
          "title": "3 finger handcam gameplay solo vs squad poco x3 pro 60fps 120hz 360hz game turbo SD860 Prosecser 4kr",
          "description": "",
          "thumbnails": {
            "default": {
              "url": "https://i.ytimg.com/vi/dRZ1m1LnGXg/default.jpg",
              "width": 120,
              "height": 90
            },
            "medium": {
              "url": "https://i.ytimg.com/vi/dRZ1m1LnGXg/mqdefault.jpg",
              "width": 320,
              "height": 180
            },
            "high": {
              "url": "https://i.ytimg.com/vi/dRZ1m1LnGXg/hqdefault.jpg",
              "width": 480,
              "height": 360
            }
          },
          "channelTitle": "Gamer Tikam",
          "liveBroadcastContent": "none",
          "publishTime": "2024-04-24T12:40:17Z"
        }
      },
      {
        "kind": "youtube#searchResult",
        "etag": "JCqi7_2ZKaOpM69-_e24eLgTZiU",
        "id": {
          "kind": "youtube#video",
          "videoId": "_i0r4-wM7mw"
        },
        "snippet": {
          "publishedAt": "2024-09-06T06:30:21Z",
          "channelId": "UChRC_1EovxI0_fRj4w_Zkbw",
          "title": "Kamla ne Ullu Banaya 🥹 #neetubisht #gamingchannel #gaming #gameplay #gaming #gamergirl",
          "description": "",
          "thumbnails": {
            "default": {
              "url": "https://i.ytimg.com/vi/_i0r4-wM7mw/default.jpg",
              "width": 120,
              "height": 90
            },
            "medium": {
              "url": "https://i.ytimg.com/vi/_i0r4-wM7mw/mqdefault.jpg",
              "width": 320,
              "height": 180
            },
            "high": {
              "url": "https://i.ytimg.com/vi/_i0r4-wM7mw/hqdefault.jpg",
              "width": 480,
              "height": 360
            }
          },
          "channelTitle": "Neetu Gaming",
          "liveBroadcastContent": "none",
          "publishTime": "2024-09-06T06:30:21Z"
        }
      },
      {
        "kind": "youtube#searchResult",
        "etag": "8j3JwmJdujqKRk9gWdqnS0sKMZc",
        "id": {
          "kind": "youtube#video",
          "videoId": "qupWRCYbqdM"
        },
        "snippet": {
          "publishedAt": "2024-07-20T05:40:37Z",
          "channelId": "UCP7WsVTkbPP9EaIFIUgwngg",
          "title": "No Way To Escape 🤯 Welcome To Peak 🎯 Garena free fire #shorts #freefire #youtubeshorts",
          "description": "shorts #short #freefireshorts #freefire #viral #trending #funnyshorts #trendingshorts #youtubeshorts #ytshorts #viralshorts ...",
          "thumbnails": {
            "default": {
              "url": "https://i.ytimg.com/vi/qupWRCYbqdM/default.jpg",
              "width": 120,
              "height": 90
            },
            "medium": {
              "url": "https://i.ytimg.com/vi/qupWRCYbqdM/mqdefault.jpg",
              "width": 320,
              "height": 180
            },
            "high": {
              "url": "https://i.ytimg.com/vi/qupWRCYbqdM/hqdefault.jpg",
              "width": 480,
              "height": 360
            }
          },
          "channelTitle": "PK GAMERS",
          "liveBroadcastContent": "none",
          "publishTime": "2024-07-20T05:40:37Z"
        }
      },
      {
        "kind": "youtube#searchResult",
        "etag": "swcr5nOFa_4rqPTJpmkRP0-zw40",
        "id": {
          "kind": "youtube#video",
          "videoId": "y-DvcX1XaZ4"
        },
        "snippet": {
          "publishedAt": "2025-03-11T12:05:29Z",
          "channelId": "UCBIgj_1GbEipa2ybF7fXBAQ",
          "title": "YADAV GAMER💀 DESTROY TONDE DAI☠️, SONEETA 🥰&amp; GTK 🩻",
          "description": "",
          "thumbnails": {
            "default": {
              "url": "https://i.ytimg.com/vi/y-DvcX1XaZ4/default.jpg",
              "width": 120,
              "height": 90
            },
            "medium": {
              "url": "https://i.ytimg.com/vi/y-DvcX1XaZ4/mqdefault.jpg",
              "width": 320,
              "height": 180
            },
            "high": {
              "url": "https://i.ytimg.com/vi/y-DvcX1XaZ4/hqdefault.jpg",
              "width": 480,
              "height": 360
            }
          },
          "channelTitle": "YADAV GAMER",
          "liveBroadcastContent": "none",
          "publishTime": "2025-03-11T12:05:29Z"
        }
      },
      {
        "kind": "youtube#searchResult",
        "etag": "3-uqLwufHimRKYjUAPOKX5sIovA",
        "id": {
          "kind": "youtube#video",
          "videoId": "KSfESMkwI_M"
        },
        "snippet": {
          "publishedAt": "2025-01-20T00:08:37Z",
          "channelId": "UCRFSF9WS_g0wqm32kjJ-jNw",
          "title": "The US Could BAN VIDEO GAMES #shorts",
          "description": "Banning Elden Ring is CRAZY #leagueoflegends #eldenring #darksouls #marvelrivals #xbox #gaming #skit #fyp #fypシ゚ ...",
          "thumbnails": {
            "default": {
              "url": "https://i.ytimg.com/vi/KSfESMkwI_M/default.jpg",
              "width": 120,
              "height": 90
            },
            "medium": {
              "url": "https://i.ytimg.com/vi/KSfESMkwI_M/mqdefault.jpg",
              "width": 320,
              "height": 180
            },
            "high": {
              "url": "https://i.ytimg.com/vi/KSfESMkwI_M/hqdefault.jpg",
              "width": 480,
              "height": 360
            }
          },
          "channelTitle": "jacobweeby",
          "liveBroadcastContent": "none",
          "publishTime": "2025-01-20T00:08:37Z"
        }
      },
      {
        "kind": "youtube#searchResult",
        "etag": "lbc_pe-rkYNOBUFImweL-SVVC1k",
        "id": {
          "kind": "youtube#video",
          "videoId": "UY6iQf1vc7U"
        },
        "snippet": {
          "publishedAt": "2024-10-29T04:35:13Z",
          "channelId": "UChRC_1EovxI0_fRj4w_Zkbw",
          "title": "Neetu Ne Kiya Kamla Ko Challenge☠️ #kamla #gameplay #gaming #gamer #games #horrorgaming #gmod #game",
          "description": "",
          "thumbnails": {
            "default": {
              "url": "https://i.ytimg.com/vi/UY6iQf1vc7U/default.jpg",
              "width": 120,
              "height": 90
            },
            "medium": {
              "url": "https://i.ytimg.com/vi/UY6iQf1vc7U/mqdefault.jpg",
              "width": 320,
              "height": 180
            },
            "high": {
              "url": "https://i.ytimg.com/vi/UY6iQf1vc7U/hqdefault.jpg",
              "width": 480,
              "height": 360
            }
          },
          "channelTitle": "Neetu Gaming",
          "liveBroadcastContent": "none",
          "publishTime": "2024-10-29T04:35:13Z"
        }
      },
      {
        "kind": "youtube#searchResult",
        "etag": "jHnsxVQIDqPrUmhpd5Ecrsq4Kd4",
        "id": {
          "kind": "youtube#video",
          "videoId": "dWLrenmD-2E"
        },
        "snippet": {
          "publishedAt": "2025-01-24T22:38:41Z",
          "channelId": "UCoWliOvugpnkRXzjHXWiO3w",
          "title": "Every Video Game Intro…",
          "description": "",
          "thumbnails": {
            "default": {
              "url": "https://i.ytimg.com/vi/dWLrenmD-2E/default.jpg",
              "width": 120,
              "height": 90
            },
            "medium": {
              "url": "https://i.ytimg.com/vi/dWLrenmD-2E/mqdefault.jpg",
              "width": 320,
              "height": 180
            },
            "high": {
              "url": "https://i.ytimg.com/vi/dWLrenmD-2E/hqdefault.jpg",
              "width": 480,
              "height": 360
            }
          },
          "channelTitle": "NicsNite",
          "liveBroadcastContent": "none",
          "publishTime": "2025-01-24T22:38:41Z"
        }
      },
      {
        "kind": "youtube#searchResult",
        "etag": "T1uLkQVyN_kchNlL5JGoWNSb2Vk",
        "id": {
          "kind": "youtube#video",
          "videoId": "x-xelO_xyfA"
        },
        "snippet": {
          "publishedAt": "2025-01-02T03:44:42Z",
          "channelId": "UChEH_eKDZrOJjhcdzYjI4jA",
          "title": "2025 MIGHT be goated for gaming 😭🎮",
          "description": "",
          "thumbnails": {
            "default": {
              "url": "https://i.ytimg.com/vi/x-xelO_xyfA/default.jpg",
              "width": 120,
              "height": 90
            },
            "medium": {
              "url": "https://i.ytimg.com/vi/x-xelO_xyfA/mqdefault.jpg",
              "width": 320,
              "height": 180
            },
            "high": {
              "url": "https://i.ytimg.com/vi/x-xelO_xyfA/hqdefault.jpg",
              "width": 480,
              "height": 360
            }
          },
          "channelTitle": "BucketJosh",
          "liveBroadcastContent": "none",
          "publishTime": "2025-01-02T03:44:42Z"
        }
      },
      {
        "kind": "youtube#searchResult",
        "etag": "6kleUpYJS8QcHDGGCO6et4jryCU",
        "id": {
          "kind": "youtube#video",
          "videoId": "Um-uqtr6fcE"
        },
        "snippet": {
          "publishedAt": "2024-05-10T01:30:12Z",
          "channelId": "UClCe18fwE4Gtr7vgqka1Zlg",
          "title": "Funniest Roof Escape From Twins House 😎 #gamingengineer",
          "description": "Roof Escape From Bob & Buck House / Horror Game #liveengineer #gameplay #horrorstories #shorts #thetwins Granny ...",
          "thumbnails": {
            "default": {
              "url": "https://i.ytimg.com/vi/Um-uqtr6fcE/default.jpg",
              "width": 120,
              "height": 90
            },
            "medium": {
              "url": "https://i.ytimg.com/vi/Um-uqtr6fcE/mqdefault.jpg",
              "width": 320,
              "height": 180
            },
            "high": {
              "url": "https://i.ytimg.com/vi/Um-uqtr6fcE/hqdefault.jpg",
              "width": 480,
              "height": 360
            }
          },
          "channelTitle": "Live Engineer",
          "liveBroadcastContent": "none",
          "publishTime": "2024-05-10T01:30:12Z"
        }
      },
      {
        "kind": "youtube#searchResult",
        "etag": "heMlC1lRQoevUua-QVom_Lft664",
        "id": {
          "kind": "youtube#video",
          "videoId": "_c5nTXIlZ6g"
        },
        "snippet": {
          "publishedAt": "2025-02-04T19:30:07Z",
          "channelId": "UCtZO2c3i1PrtwyeaxaIYHKA",
          "title": "Squid Game Season 3 😂😂 #funny #squidgame #memes #shorts",
          "description": "",
          "thumbnails": {
            "default": {
              "url": "https://i.ytimg.com/vi/_c5nTXIlZ6g/default.jpg",
              "width": 120,
              "height": 90
            },
            "medium": {
              "url": "https://i.ytimg.com/vi/_c5nTXIlZ6g/mqdefault.jpg",
              "width": 320,
              "height": 180
            },
            "high": {
              "url": "https://i.ytimg.com/vi/_c5nTXIlZ6g/hqdefault.jpg",
              "width": 480,
              "height": 360
            }
          },
          "channelTitle": "Keepest",
          "liveBroadcastContent": "none",
          "publishTime": "2025-02-04T19:30:07Z"
        }
      },
      {
        "kind": "youtube#searchResult",
        "etag": "wrlcQFmPxj9hnBKsk0SamF4RniI",
        "id": {
          "kind": "youtube#video",
          "videoId": "jdmPSjon6w4"
        },
        "snippet": {
          "publishedAt": "2025-03-01T10:37:13Z",
          "channelId": "UCNNdYhLEd4aAivW_V9GNOMQ",
          "title": "I Tried &quot;Gaming&quot; In EVERY Airplane Seat",
          "description": "I Tried \"Gaming\" In EVERY Plane Seat... Big Thanks to Odoo for making this video possible, go check them out by clicking the link ...",
          "thumbnails": {
            "default": {
              "url": "https://i.ytimg.com/vi/jdmPSjon6w4/default.jpg",
              "width": 120,
              "height": 90
            },
            "medium": {
              "url": "https://i.ytimg.com/vi/jdmPSjon6w4/mqdefault.jpg",
              "width": 320,
              "height": 180
            },
            "high": {
              "url": "https://i.ytimg.com/vi/jdmPSjon6w4/hqdefault.jpg",
              "width": 480,
              "height": 360
            }
          },
          "channelTitle": "Dantic",
          "liveBroadcastContent": "none",
          "publishTime": "2025-03-01T10:37:13Z"
        }
      },
      {
        "kind": "youtube#searchResult",
        "etag": "hYLaTPn56lRsd95Nsc1PXoFP2Kw",
        "id": {
          "kind": "youtube#channel",
          "channelId": "UCIPPMRA040LQr5QPyJEbmXA"
        },
        "snippet": {
          "publishedAt": "2020-04-07T18:46:13Z",
          "channelId": "UCIPPMRA040LQr5QPyJEbmXA",
          "title": "MrBeast Gaming",
          "description": "Go Watch Beast Games! https://unfur.ly/BeastGames MrBeast Gaming - SUBSCRIBE OR ELSE.",
          "thumbnails": {
            "default": {
              "url": "https://yt3.ggpht.com/ytc/AIdro_lMiSL6eHqg2dVxvll6mVMeXo1qVak4TZ4_7mEWdobRRCk=s88-c-k-c0xffffffff-no-rj-mo"
            },
            "medium": {
              "url": "https://yt3.ggpht.com/ytc/AIdro_lMiSL6eHqg2dVxvll6mVMeXo1qVak4TZ4_7mEWdobRRCk=s240-c-k-c0xffffffff-no-rj-mo"
            },
            "high": {
              "url": "https://yt3.ggpht.com/ytc/AIdro_lMiSL6eHqg2dVxvll6mVMeXo1qVak4TZ4_7mEWdobRRCk=s800-c-k-c0xffffffff-no-rj-mo"
            }
          },
          "channelTitle": "MrBeast Gaming",
          "liveBroadcastContent": "none",
          "publishTime": "2020-04-07T18:46:13Z"
        }
      },
      {
        "kind": "youtube#searchResult",
        "etag": "-xiy--JFc9L17fAB9QvzfLgeB-I",
        "id": {
          "kind": "youtube#video",
          "videoId": "XlPBaYkyyA4"
        },
        "snippet": {
          "publishedAt": "2024-11-28T13:30:30Z",
          "channelId": "UCLGHEUaREx_FtNrqfJ8gXIA",
          "title": "WHAT&#39;S INSIDE A MOON BALL? 🤔🌕⚾ #shorts #youtubeshorts #cricket #collection #unboxing",
          "description": "VOTE FOR ALIEN BALL ⚾ Join this channel to get access to perks: ...",
          "thumbnails": {
            "default": {
              "url": "https://i.ytimg.com/vi/XlPBaYkyyA4/default.jpg",
              "width": 120,
              "height": 90
            },
            "medium": {
              "url": "https://i.ytimg.com/vi/XlPBaYkyyA4/mqdefault.jpg",
              "width": 320,
              "height": 180
            },
            "high": {
              "url": "https://i.ytimg.com/vi/XlPBaYkyyA4/hqdefault.jpg",
              "width": 480,
              "height": 360
            }
          },
          "channelTitle": "Box Of Vengeance",
          "liveBroadcastContent": "none",
          "publishTime": "2024-11-28T13:30:30Z"
        }
      },
      {
        "kind": "youtube#searchResult",
        "etag": "zSjsR668uUhKTkpX8aFFH8_0BrA",
        "id": {
          "kind": "youtube#video",
          "videoId": "EEaH_sitgFY"
        },
        "snippet": {
          "publishedAt": "2024-11-18T14:25:21Z",
          "channelId": "UCgLEJLbJ4wXAR1WlhHwyqeg",
          "title": "Techno gamerz scared😞on this moment😱#shorts #top #trollface #trending #viralshorts #technogamerz",
          "description": "Techno gamerz scared  on this moment  #shorts #top #trollface #trending #viralshorts #technogamerz #popular #minecraft ...",
          "thumbnails": {
            "default": {
              "url": "https://i.ytimg.com/vi/EEaH_sitgFY/default.jpg",
              "width": 120,
              "height": 90
            },
            "medium": {
              "url": "https://i.ytimg.com/vi/EEaH_sitgFY/mqdefault.jpg",
              "width": 320,
              "height": 180
            },
            "high": {
              "url": "https://i.ytimg.com/vi/EEaH_sitgFY/hqdefault.jpg",
              "width": 480,
              "height": 360
            }
          },
          "channelTitle": "Indian Gaming Gamer",
          "liveBroadcastContent": "none",
          "publishTime": "2024-11-18T14:25:21Z"
        }
      },
      {
        "kind": "youtube#searchResult",
        "etag": "ZqA_WMHb4H89l0XAi8hRaVnXK4E",
        "id": {
          "kind": "youtube#video",
          "videoId": "BlHji1erWp0"
        },
        "snippet": {
          "publishedAt": "2024-10-17T08:41:07Z",
          "channelId": "UCj0sKQk9qjiIfNH22ZBWpxw",
          "title": "BEST gaming phone 🔥",
          "description": "\"BEST gaming phone \" is this the best phone to play pubg mobile / bgmi on? #pubgmobile #pubgmobile #bgmi :B2kmobi.",
          "thumbnails": {
            "default": {
              "url": "https://i.ytimg.com/vi/BlHji1erWp0/default.jpg",
              "width": 120,
              "height": 90
            },
            "medium": {
              "url": "https://i.ytimg.com/vi/BlHji1erWp0/mqdefault.jpg",
              "width": 320,
              "height": 180
            },
            "high": {
              "url": "https://i.ytimg.com/vi/BlHji1erWp0/hqdefault.jpg",
              "width": 480,
              "height": 360
            }
          },
          "channelTitle": "Panda",
          "liveBroadcastContent": "none",
          "publishTime": "2024-10-17T08:41:07Z"
        }
      },
      {
        "kind": "youtube#searchResult",
        "etag": "aEjeJCrBasKS3VbjZt-NmgM0tpg",
        "id": {
          "kind": "youtube#video",
          "videoId": "uSloWpsUHBI"
        },
        "snippet": {
          "publishedAt": "2025-03-12T10:21:55Z",
          "channelId": "UCD5EC8IWhOFalXtePCkhJTA",
          "title": "100 Level Free Fire Player Vs Tonde Gamer Collection Battle 😱 #shorts #freefire #tondegamer",
          "description": "Live Channel :- https://www.youtube.com/@TondeisLive02 X Link ( Twitter ) https://x.com/TondeGamer Instagram: ...",
          "thumbnails": {
            "default": {
              "url": "https://i.ytimg.com/vi/uSloWpsUHBI/default.jpg",
              "width": 120,
              "height": 90
            },
            "medium": {
              "url": "https://i.ytimg.com/vi/uSloWpsUHBI/mqdefault.jpg",
              "width": 320,
              "height": 180
            },
            "high": {
              "url": "https://i.ytimg.com/vi/uSloWpsUHBI/hqdefault.jpg",
              "width": 480,
              "height": 360
            }
          },
          "channelTitle": "Tonde Gamer",
          "liveBroadcastContent": "none",
          "publishTime": "2025-03-12T10:21:55Z"
        }
      },
      {
        "kind": "youtube#searchResult",
        "etag": "fEl90G8QxD4pV5HOeb6WGEqi7FY",
        "id": {
          "kind": "youtube#video",
          "videoId": "NpytLI-FFew"
        },
        "snippet": {
          "publishedAt": "2025-02-22T09:00:22Z",
          "channelId": "UCrddA2HWyVhVmU3X63oJMgg",
          "title": "Age of Apes ads review new level: Ape War Begins #gaming #fortnite #games",
          "description": "",
          "thumbnails": {
            "default": {
              "url": "https://i.ytimg.com/vi/NpytLI-FFew/default.jpg",
              "width": 120,
              "height": 90
            },
            "medium": {
              "url": "https://i.ytimg.com/vi/NpytLI-FFew/mqdefault.jpg",
              "width": 320,
              "height": 180
            },
            "high": {
              "url": "https://i.ytimg.com/vi/NpytLI-FFew/hqdefault.jpg",
              "width": 480,
              "height": 360
            }
          },
          "channelTitle": "AOA Review",
          "liveBroadcastContent": "none",
          "publishTime": "2025-02-22T09:00:22Z"
        }
      },
      {
        "kind": "youtube#searchResult",
        "etag": "I5hmbvWyFu-8kjgm2pPNoKjD3sU",
        "id": {
          "kind": "youtube#video",
          "videoId": "bRT0l1620Y8"
        },
        "snippet": {
          "publishedAt": "2025-02-02T15:31:31Z",
          "channelId": "UCysqPMuwN5fWnx_KSJAoUhg",
          "title": "Indian bike driving 3d All Character Power😱#gaming #ytshorts #shorts",
          "description": "Indian bike driving 3d All Character Power  #gaming #ytshorts #shorts Indian bike new cheat code Indian bike stunt 3d game ...",
          "thumbnails": {
            "default": {
              "url": "https://i.ytimg.com/vi/bRT0l1620Y8/default.jpg",
              "width": 120,
              "height": 90
            },
            "medium": {
              "url": "https://i.ytimg.com/vi/bRT0l1620Y8/mqdefault.jpg",
              "width": 320,
              "height": 180
            },
            "high": {
              "url": "https://i.ytimg.com/vi/bRT0l1620Y8/hqdefault.jpg",
              "width": 480,
              "height": 360
            }
          },
          "channelTitle": "PRAVEEN PALRIYA ",
          "liveBroadcastContent": "none",
          "publishTime": "2025-02-02T15:31:31Z"
        }
      },
      {
        "kind": "youtube#searchResult",
        "etag": "695WdWWin3l3TTSKimUMWFouY8U",
        "id": {
          "kind": "youtube#video",
          "videoId": "hyOq74hQ6bw"
        },
        "snippet": {
          "publishedAt": "2025-02-14T20:08:20Z",
          "channelId": "UCOZsMcbEwVbEIKW4nMNTIVA",
          "title": "WHAT DID I JUST GET!!?? Blox Fruits",
          "description": "Buy The PLUSHIE: https://lootbloc.com/products/limited-kitt-gaming-kittcat-plushie ⭐SOCIAL LINKS⭐: Discord: ...",
          "thumbnails": {
            "default": {
              "url": "https://i.ytimg.com/vi/hyOq74hQ6bw/default.jpg",
              "width": 120,
              "height": 90
            },
            "medium": {
              "url": "https://i.ytimg.com/vi/hyOq74hQ6bw/mqdefault.jpg",
              "width": 320,
              "height": 180
            },
            "high": {
              "url": "https://i.ytimg.com/vi/hyOq74hQ6bw/hqdefault.jpg",
              "width": 480,
              "height": 360
            }
          },
          "channelTitle": "Kitt Gaming",
          "liveBroadcastContent": "none",
          "publishTime": "2025-02-14T20:08:20Z"
        }
      },
      {
        "kind": "youtube#searchResult",
        "etag": "uRDJz_GKfketMRGWgNuLpcsnhXA",
        "id": {
          "kind": "youtube#video",
          "videoId": "KimAJSHsTTs"
        },
        "snippet": {
          "publishedAt": "2024-09-07T21:24:08Z",
          "channelId": "UC8mUYbbox7w9WjpynlyQnyA",
          "title": "Meet the Perfect Astro Bot Duo! #gamingshorts  #playstation #astrobot #gaming #ps5",
          "description": "",
          "thumbnails": {
            "default": {
              "url": "https://i.ytimg.com/vi/KimAJSHsTTs/default.jpg",
              "width": 120,
              "height": 90
            },
            "medium": {
              "url": "https://i.ytimg.com/vi/KimAJSHsTTs/mqdefault.jpg",
              "width": 320,
              "height": 180
            },
            "high": {
              "url": "https://i.ytimg.com/vi/KimAJSHsTTs/hqdefault.jpg",
              "width": 480,
              "height": 360
            }
          },
          "channelTitle": "CharSpective",
          "liveBroadcastContent": "none",
          "publishTime": "2024-09-07T21:24:08Z"
        }
      },
      {
        "kind": "youtube#searchResult",
        "etag": "Im6dX0__OiyGZ5Lf1a7LljNZF94",
        "id": {
          "kind": "youtube#video",
          "videoId": "DIR6487etPk"
        },
        "snippet": {
          "publishedAt": "2024-09-21T02:22:54Z",
          "channelId": "UCsgZTV65W5UdodSm_ufJzmA",
          "title": "The game is sad &amp; beautiful🥺😭 #animation #art #gaming #games #shortsfeed #shorts #reels #gameplay",
          "description": "",
          "thumbnails": {
            "default": {
              "url": "https://i.ytimg.com/vi/DIR6487etPk/default.jpg",
              "width": 120,
              "height": 90
            },
            "medium": {
              "url": "https://i.ytimg.com/vi/DIR6487etPk/mqdefault.jpg",
              "width": 320,
              "height": 180
            },
            "high": {
              "url": "https://i.ytimg.com/vi/DIR6487etPk/hqdefault.jpg",
              "width": 480,
              "height": 360
            }
          },
          "channelTitle": "CandyKola",
          "liveBroadcastContent": "none",
          "publishTime": "2024-09-21T02:22:54Z"
        }
      },
      {
        "kind": "youtube#searchResult",
        "etag": "o_loxuIwOzPpBvSU5Kbg-Vksflg",
        "id": {
          "kind": "youtube#video",
          "videoId": "I83AEW4GdEw"
        },
        "snippet": {
          "publishedAt": "2022-09-18T02:43:18Z",
          "channelId": "UCZN2dtGM2V12A4kcqV-WJnQ",
          "title": "I ain’t trying to flex but… #gamingshorts #gamingsetup #gamingroom #gamer #theultimatenerd",
          "description": "",
          "thumbnails": {
            "default": {
              "url": "https://i.ytimg.com/vi/I83AEW4GdEw/default.jpg",
              "width": 120,
              "height": 90
            },
            "medium": {
              "url": "https://i.ytimg.com/vi/I83AEW4GdEw/mqdefault.jpg",
              "width": 320,
              "height": 180
            },
            "high": {
              "url": "https://i.ytimg.com/vi/I83AEW4GdEw/hqdefault.jpg",
              "width": 480,
              "height": 360
            }
          },
          "channelTitle": "dinocornel",
          "liveBroadcastContent": "none",
          "publishTime": "2022-09-18T02:43:18Z"
        }
      }
    ]
  }
  